{
  "$schema": "https://raw.githubusercontent.com/microsoft/vcpkg-tool/main/docs/vcpkg-configuration.schema.json",
  "default-registry": {
    "kind": "git",
    "repository": "https://github.com/microsoft/vcpkg",
    "baseline": "15d59ec83cc48b7fb9ecc1ef667c401ef4270fea"
  },
  "registries": [
    {
      "kind": "git",
      "repository": "https://github.com/Zinn-o-Matics/vcpkg-registry",
      "baseline": "ad12fd5c98f02eebfadf1814635e1cfa3e364a01",
      "packages": [
        "arcdps-extension",
        "arcdps-unofficial-extras",
        "imgui"
      ]
    }
  ]
}